dbdragoness/__init__.py
dbdragoness/__main__.py
dbdragoness/app.py
dbdragoness/cli.py
dbdragoness/db_handler.py
dbdragoness/db_registry.py
dbdragoness/duckdb_handler.py
dbdragoness/mongodb_handler.py
dbdragoness/mysql_credentials_clearer.py
dbdragoness/mysql_handler.py
dbdragoness/nosql_handler.py
dbdragoness/postgresql_credentials_clearer.py
dbdragoness/postgresql_handler.py
dbdragoness/query_history_manager.py
dbdragoness/sql_handler.py
dbdragoness/sqlite_handler.py
dbdragoness/tinydb_handler.py
dbdragoness/data/query_history.json
dbdragoness/static/style.css
dbdragoness/static/react/Logo.png
dbdragoness/static/react/index.html
dbdragoness/static/react/vite.svg
dbdragoness/static/react/assets/Logo-DbMALHZL.png
dbdragoness/static/react/assets/_basePickBy-D8sEi8GF.js
dbdragoness/static/react/assets/_baseUniq-JITOn4Fp.js
dbdragoness/static/react/assets/arc-Dj8jtJdt.js
dbdragoness/static/react/assets/architectureDiagram-VXUJARFQ-Cuu5LbVa.js
dbdragoness/static/react/assets/blockDiagram-VD42YOAC-C3MZcybf.js
dbdragoness/static/react/assets/c4Diagram-YG6GDRKO-CTmD1pg9.js
dbdragoness/static/react/assets/channel-B4A9n_QW.js
dbdragoness/static/react/assets/chunk-4BX2VUAB-B5IHJqvj.js
dbdragoness/static/react/assets/chunk-55IACEB6-DSZRWCW1.js
dbdragoness/static/react/assets/chunk-B4BG7PRW-CzCyubqk.js
dbdragoness/static/react/assets/chunk-DI55MBZ5-BzCpXZYR.js
dbdragoness/static/react/assets/chunk-FMBD7UC4-CXh3V-ta.js
dbdragoness/static/react/assets/chunk-QN33PNHL-RNBzkk3I.js
dbdragoness/static/react/assets/chunk-QZHKN3VN-DOhwp32Q.js
dbdragoness/static/react/assets/chunk-TZMSLE5B-SkUAjpUS.js
dbdragoness/static/react/assets/classDiagram-2ON5EDUG-BhxWUvF7.js
dbdragoness/static/react/assets/classDiagram-v2-WZHVMYZB-BhxWUvF7.js
dbdragoness/static/react/assets/clone-Czvmhaan.js
dbdragoness/static/react/assets/cose-bilkent-S5V4N54A-AkSsVO9i.js
dbdragoness/static/react/assets/cytoscape.esm-CyJtwmzi.js
dbdragoness/static/react/assets/dagre-6UL2VRFP-wWGkQ6fE.js
dbdragoness-0.1.11.dist-info/licenses/LICENSE.txt
dbdragoness-0.1.11.dist-info/METADATA
dbdragoness-0.1.11.dist-info/WHEEL
dbdragoness-0.1.11.dist-info/entry_points.txt
dbdragoness-0.1.11.dist-info/top_level.txt
dbdragoness-0.1.11.dist-info/RECORD
