Metadata-Version: 2.4
Name: dbdragoness
Version: 0.1.11
Summary: A lightweight DB GUI module for SQL/NoSQL, like phpMyAdmin but Pythonic!
Author: Tulika Thampi (Dragoness)
License-Expression: MIT
Project-URL: Homepage, https://github.com/tech-dragoness/dbdragoness
Classifier: Development Status :: 3 - Alpha
Classifier: Intended Audience :: Developers
Classifier: Programming Language :: Python :: 3
Classifier: Programming Language :: Python :: 3.8
Classifier: Programming Language :: Python :: 3.9
Classifier: Programming Language :: Python :: 3.10
Requires-Python: >=3.8
License-File: LICENSE.txt
Requires-Dist: flask<3.0.0,>=2.3.0
Requires-Dist: click<9.0.0,>=8.1.0
Requires-Dist: sqlalchemy<3.0.0,>=2.0.0
Requires-Dist: pymysql<2.0.0,>=1.1.0
Requires-Dist: psycopg2-binary<3.0.0,>=2.9.0
Requires-Dist: duckdb-engine<1.0.0,>=0.9.0
Requires-Dist: tinydb<5.0.0,>=4.8.0
Requires-Dist: pymongo<5.0.0,>=4.6.0
Requires-Dist: keyring<25.0.0,>=24.0.0
Requires-Dist: cryptography<42.0.0,>=41.0.0
Provides-Extra: dev
Requires-Dist: pytest>=7.4.0; extra == "dev"
Requires-Dist: pytest-cov>=4.1.0; extra == "dev"
Requires-Dist: black>=23.0.0; extra == "dev"
Requires-Dist: flake8>=6.0.0; extra == "dev"
Dynamic: license-file
